{
  "masechta": "Avodah Zarah",
  "daf": 54,
  "amud": "a-b",
  "macro_segments": [
    {
      "title": "Mizbeach and Bimos: Physical Destruction and Continued Use",
      "display_title": "Mizbeach vs. Bimos",
      "timestamp": "00:00",
      "micro_segments": [
        {
          "title": "Introduction: Distinguishing a Mizbeach (Altar) from a Bimos (Stand)",
          "display_title": "Mizbeach/Bimos Intro",
          "timestamp": "00:00"
        },
        {
          "title": "Physical Composition: One Stone vs. Many Stones",
          "display_title": "Stone Composition",
          "timestamp": "01:01"
        },
        {
          "title": "Biblical Source and Majority Destruction Principle",
          "display_title": "Biblical Source",
          "timestamp": "01:13"
        }
      ]
    },
    {
      "title": "The Status of Worshipped Animals (Ne'evad) and Ownership Restrictions",
      "display_title": "Ne'evad Animals",
      "timestamp": "02:29",
      "micro_segments": [
        {
          "title": "Baraita: One's Own Animal vs. Friend's Animal",
          "display_title": "Own vs. Friend",
          "timestamp": "02:29"
        },
        {
          "title": "Definition of Ne'evad: Worshipped Under All Circumstances",
          "display_title": "Ne'evad Definition",
          "timestamp": "02:37"
        },
        {
          "title": "Ones (Forced Worship): Interpretation and Challenge",
          "display_title": "Ones/Forced",
          "timestamp": "04:08"
        },
        {
          "title": "Rami Bar Chama's Position: Forced Worship by Non-Jews",
          "display_title": "Rami Bar Chama",
          "timestamp": "04:54"
        }
      ]
    },
    {
      "title": "The Distinction Between Did Not Do the Act vs. Did It But Exempt",
      "display_title": "Act vs. Exempt",
      "timestamp": "06:54",
      "micro_segments": [
        {
          "title": "Rabbi Zeira's Challenge: Torah Exempts the Forced",
          "display_title": "Rabbi Zeira",
          "timestamp": "06:54"
        },
        {
          "title": "Rava's Resolution: Public vs. Private and Kiddush Hashem",
          "display_title": "Rava/Kiddush Hashem",
          "timestamp": "08:29"
        },
        {
          "title": "Tosafot's Defense: Rava Holds Idolatry Requires Martyrdom Always",
          "display_title": "Tosafot Defense",
          "timestamp": "12:01"
        }
      ]
    },
    {
      "title": "Forced Worship During Persecution and the Status of Idols",
      "display_title": "Persecution Context",
      "timestamp": "14:27",
      "micro_segments": [
        {
          "title": "Baraita: Platforms of Non-Jews During Forced Worship",
          "display_title": "Persecution Baraita",
          "timestamp": "14:27"
        },
        {
          "title": "Rava's Rebuttal: Willing Jewish Apostates in Crisis",
          "display_title": "Willing Apostates",
          "timestamp": "15:30"
        },
        {
          "title": "Rav Ashi's Clarification: Assuming Some Willing Participation",
          "display_title": "Rav Ashi",
          "timestamp": "16:16"
        }
      ]
    },
    {
      "title": "Making Another's Property Forbidden: Action and Physical Control",
      "display_title": "Property Control",
      "timestamp": "16:55",
      "micro_segments": [
        {
          "title": "Chizkiyah's Answer: Ones Means Action on the Owner's Property",
          "display_title": "Chizkiyah Answer",
          "timestamp": "16:55"
        },
        {
          "title": "Principle: Cannot Forbid What Is Not Yours Without Action",
          "display_title": "Ownership Principle",
          "timestamp": "17:10"
        },
        {
          "title": "Rav Adda Bar Ahava's Challenge: Bimos vs. Ne'evad",
          "display_title": "Rav Adda Challenge",
          "timestamp": "17:53"
        },
        {
          "title": "Rav Adda's Revision: Action Must Be Directed at the Animal Itself",
          "display_title": "Action on Animal",
          "timestamp": "18:59"
        }
      ]
    },
    {
      "title": "Physical Actions and Transfer of Forbidden Status to Others' Property",
      "display_title": "Physical Acts Transfer",
      "timestamp": "19:33",
      "micro_segments": [
        {
          "title": "Ulla's Teaching: Bowing Does Not Forbid Friend's Animal",
          "display_title": "Ulla Teaching",
          "timestamp": "19:33"
        },
        {
          "title": "Exception: Physical Actions Do Forbid Friend's Property",
          "display_title": "Action Exception",
          "timestamp": "20:05"
        },
        {
          "title": "Rav Nachman's Response: Rav Huna Already Taught This in Babylon",
          "display_title": "Rav Nachman",
          "timestamp": "20:15"
        },
        {
          "title": "Rav Huna's Case: Slaughtering Another's Animal in Front of Idol",
          "display_title": "Rav Huna Case",
          "timestamp": "20:35"
        }
      ]
    },
    {
      "title": "Sources for the Principle: Making Others' Property Forbidden",
      "display_title": "Sources",
      "timestamp": "22:18",
      "micro_segments": [
        {
          "title": "Attempted Source: The Kohanim of Beit Chonyo",
          "display_title": "Kohanim Source",
          "timestamp": "22:18"
        },
        {
          "title": "Rejected: Different Principle (Fine, Not Status Change)",
          "display_title": "Rejected Source",
          "timestamp": "22:29"
        },
        {
          "title": "Better Source: Stones of the Altar (Avoided Disposal)",
          "display_title": "Altar Stones",
          "timestamp": "23:04"
        },
        {
          "title": "Alternative: Rav Pappa's Ownerlessness Theory",
          "display_title": "Ownerlessness",
          "timestamp": "23:54"
        },
        {
          "title": "Vessels Used by King Achaz for Idolatry",
          "display_title": "Achaz Vessels",
          "timestamp": "24:25"
        }
      ]
    },
    {
      "title": "Extension: Non-Owned Objects (Ground) and Money as Payment for Idols",
      "display_title": "Ground/Money Status",
      "timestamp": "25:40",
      "micro_segments": [
        {
          "title": "Rav Dimi: Bowing to Natural Ground Does Not Forbid It",
          "display_title": "Natural Ground",
          "timestamp": "25:40"
        },
        {
          "title": "Exception: Digging Wells or Caves in Ground",
          "display_title": "Digging Exception",
          "timestamp": "26:12"
        },
        {
          "title": "Rav Shmuel Bar Yehuda: Animals as Payment Exchange",
          "display_title": "Payment Exchange",
          "timestamp": "26:59"
        },
        {
          "title": "Introduction: Money Paid for Idolatry",
          "display_title": "Money Paid",
          "timestamp": "27:26"
        }
      ]
    },
    {
      "title": "Debate on the Transmission of Forbidden Status Through Successive Exchanges",
      "display_title": "Exchanges Debate",
      "timestamp": "28:15",
      "micro_segments": [
        {
          "title": "First Opinion: Only Direct Payment Is Forbidden",
          "display_title": "Direct Payment Only",
          "timestamp": "28:15"
        },
        {
          "title": "Second Opinion: Forbidden Status Extends Infinitely",
          "display_title": "Infinite Extension",
          "timestamp": "28:26"
        },
        {
          "title": "Source: Biblical Proof (Abomination and Aversion)",
          "display_title": "Biblical Source",
          "timestamp": "29:08"
        },
        {
          "title": "Limiting Principle: Kamo'hu Restricts to Direct Exchange Only",
          "display_title": "Kamo'hu Limit",
          "timestamp": "29:34"
        }
      ]
    },
    {
      "title": "Comparison with Shemitah (Sabbatical) Produce and Transfer of Status",
      "display_title": "Shemitah Parallel",
      "timestamp": "31:27",
      "micro_segments": [
        {
          "title": "Analogy: Shemitah Produce and Sanctity Transfer",
          "display_title": "Sanctity Transfer",
          "timestamp": "31:27"
        },
        {
          "title": "Hermeneutical Principle: Two Verses Indicate Exception, Not Rule",
          "display_title": "Two Verses Rule",
          "timestamp": "31:37"
        },
        {
          "title": "Distinction: Kedesh vs. Shemitah (Original and Transferred)",
          "display_title": "Kedesh vs. Shemitah",
          "timestamp": "32:54"
        },
        {
          "title": "Continuous Exchange Rule: Status Travels Through All Exchanges",
          "display_title": "Continuous Exchange",
          "timestamp": "34:08"
        }
      ]
    },
    {
      "title": "Philosophical Reflection: Why God Permits Idolatry in the World",
      "display_title": "God Permits Idolatry",
      "timestamp": "36:47",
      "micro_segments": [
        {
          "title": "Mishnah: Elders Asked by Roman Philosophers",
          "display_title": "Mishnah Question",
          "timestamp": "36:47"
        },
        {
          "title": "Answer: Necessary Objects (Sun, Moon, Stars) Cannot Be Destroyed",
          "display_title": "Natural Objects",
          "timestamp": "37:21"
        },
        {
          "title": "Talmudic Version and Rav's Response: World Operates by Natural Law",
          "display_title": "Natural Law",
          "timestamp": "39:34"
        },
        {
          "title": "Alternative Explanation: Sinners Will Eventually Face Judgment",
          "display_title": "Judgment",
          "timestamp": "39:55"
        },
        {
          "title": "Second Example: Theft and Planting Stolen Seeds",
          "display_title": "Theft Example",
          "timestamp": "40:45"
        },
        {
          "title": "Third Example: Adultery and Divine Complicity",
          "display_title": "Adultery Example",
          "timestamp": "41:18"
        },
        {
          "title": "Reish Lakish's Teaching: God's Reluctant Participation in Creation",
          "display_title": "Reish Lakish",
          "timestamp": "41:40"
        }
      ]
    }
  ],
  "topical_tags": [
    {
      "term": "Ne'evad (worshipped object)",
      "timestamps": [
        "02:37",
        "03:36",
        "04:08",
        "16:55",
        "18:04",
        "18:30"
      ]
    },
    {
      "term": "Ones (forced/coerced action)",
      "timestamps": [
        "04:08",
        "05:00",
        "06:54",
        "08:29",
        "14:27"
      ]
    },
    {
      "term": "Kiddush Hashem (sanctification of God's name)",
      "timestamps": [
        "09:10",
        "10:03",
        "12:01"
      ]
    },
    {
      "term": "Yehareg v'lo ya'avor (give up life rather than violate)",
      "timestamps": [
        "05:32",
        "09:46",
        "10:01"
      ]
    },
    {
      "term": "Ma'aseh (physical action/act)",
      "timestamps": [
        "19:17",
        "20:05",
        "21:47",
        "23:00"
      ]
    },
    {
      "term": "Ein adam oser davar she'eino shelo (cannot forbid what is not one's own)",
      "timestamps": [
        "17:21",
        "24:10",
        "25:35"
      ]
    },
    {
      "term": "Rami Bar Chama",
      "timestamps": [
        "04:54",
        "15:20"
      ]
    },
    {
      "term": "Rabbi Zeira",
      "timestamps": [
        "06:54",
        "07:10",
        "10:20"
      ]
    },
    {
      "term": "Rava",
      "timestamps": [
        "08:29",
        "12:04",
        "15:30"
      ]
    },
    {
      "term": "Chizkiyah",
      "display_title": "Chizkiyah",
      "timestamps": [
        "01:01",
        "16:55"
      ]
    },
    {
      "term": "Rav Huna",
      "timestamps": [
        "20:24",
        "20:35"
      ]
    },
    {
      "term": "Rava Dimi",
      "timestamps": [
        "25:40"
      ]
    },
    {
      "term": "Rav Shmuel Bar Yehuda",
      "timestamps": [
        "26:59"
      ]
    },
    {
      "term": "Sheni ketuvim ba'im ke'echad (two verses indicate exception)",
      "timestamps": [
        "31:37",
        "35:50"
      ]
    },
    {
      "term": "Kamo'hu (like it - limiting transfers)",
      "timestamps": [
        "29:34",
        "35:43"
      ]
    },
    {
      "term": "Shemitah (Sabbatical year produce)",
      "timestamps": [
        "31:27",
        "32:54",
        "34:08"
      ]
    },
    {
      "term": "Olam keminhago noheg (world operates by natural law)",
      "timestamps": [
        "39:55",
        "40:33",
        "41:13"
      ]
    },
    {
      "term": "Reish Lakish",
      "timestamps": [
        "41:40"
      ]
    },
    {
      "term": "Chalifin (exchange/payment for idols)",
      "timestamps": [
        "27:26",
        "28:15",
        "28:26"
      ]
    }
  ]
}