{
  "masechta": "Pesachim",
  "daf": 101,
  "amud": "b",
  "macro_segments": [
    {
      "title": "The Status of Kiddush Made in Shul: Rav vs. Shmuel on Yetziat Kiddush Without a Seudah",
      "display_title": "Kiddush in Shul",
      "timestamp": "01:01",
      "micro_segments": [
        {
          "title": "Introduction: Those Who Made Kiddush in the Synagogue",
          "display_title": "Intro: Shul Kiddush",
          "timestamp": "01:01"
        },
        {
          "title": "Rav's Position: Yetziat Kiddush Without Seudah; The Bracha Issue of Shinuy Makom",
          "display_title": "Rav's Position",
          "timestamp": "01:14"
        },
        {
          "title": "Shmuel's Position: Kiddush Only Where There Is a Seudah",
          "display_title": "Shmuel's Position",
          "timestamp": "02:04"
        },
        {
          "title": "Rav's Reasoning: Why Make Kiddush Again at Home if Already Yotzei in Shul",
          "display_title": "Rav's Reasoning",
          "timestamp": "02:14"
        },
        {
          "title": "Shmuel's Reasoning: Why Make Kiddush in Shul If One Is Not Yotzei",
          "display_title": "Shmuel's Reasoning",
          "timestamp": "02:57"
        },
        {
          "title": "The Principle of Makom Seudah and Its Application to First vs. Third Meals",
          "display_title": "Makom Seudah Principle",
          "timestamp": "03:38"
        },
        {
          "title": "Tosafot's Clarification: Makom Seudah Requires Bread, Not Just Mezonot",
          "display_title": "Tosafot on Bread",
          "timestamp": "04:40"
        },
        {
          "title": "Modern Practice: Making Kiddush in Shul When No One Eats There",
          "display_title": "Modern Practice",
          "timestamp": "05:53"
        },
        {
          "title": "The Parallel of Chazarat HaShatz: Liturgical Practice Beyond Original Purpose",
          "display_title": "Chazarat HaShatz Analogy",
          "timestamp": "06:01"
        },
        {
          "title": "The Question of Preference: Who Should Make Kiddush and the Principle of Shomea K'Oneh",
          "display_title": "Preference Question",
          "timestamp": "08:01"
        },
        {
          "title": "Tosafot on Drinking Wine: Not Required for Yetziat Kiddush",
          "display_title": "Wine Not Required",
          "timestamp": "09:02"
        }
      ]
    },
    {
      "title": "The Requirement of Makom Seudah: Evidence from Rav Huna and Abaye's Teachings",
      "display_title": "Makom Seudah Evidence",
      "timestamp": "12:01",
      "micro_segments": [
        {
          "title": "The Principle of Ein Kiddush Ela Bimkom Seudah",
          "display_title": "Ein Kiddush Principle",
          "timestamp": "12:01"
        },
        {
          "title": "Two Explanations from Rashbam: Wine's Significance and the Oneg Shabbat Framework",
          "display_title": "Rashbam's Explanations",
          "timestamp": "12:06"
        },
        {
          "title": "Rav Huna's Case: Making Kiddush on the Roof, Then Moving to the Ground Floor",
          "display_title": "Rav Huna's Case",
          "timestamp": "13:12"
        }
      ]
    },
    {
      "title": "Shinuy Makom and the Requirement for New Berachot: Yochanan vs. Chazal on Wine and Location Changes",
      "display_title": "Shinuy Makom",
      "timestamp": "13:41",
      "micro_segments": [
        {
          "title": "Rav Anan bar Tachlifa's Testimony: The Limit of Shinuy Makom (Bayit L'Bayit)",
          "display_title": "Rav Anan's Testimony",
          "timestamp": "13:41"
        }
      ]
    },
    {
      "title": "The Requirement of Makom Seudah: Evidence from Rav Huna and Abaye's Teachings (continued)",
      "display_title": "Makom Seudah Evidence…",
      "timestamp": "15:08",
      "micro_segments": [
        {
          "title": "Tosafot's Qualification: Different Locations in the Same House With Intent",
          "display_title": "Tosafot's Qualification",
          "timestamp": "15:08"
        },
        {
          "title": "Distinction Between Different Houses vs. Different Rooms in One Building",
          "display_title": "House vs. Room Distincti…",
          "timestamp": "16:36"
        },
        {
          "title": "Application to Shul Kiddush: Making in One Location, Eating in Another",
          "display_title": "Shul Application",
          "timestamp": "18:40"
        },
        {
          "title": "Abaye's Account: Rabbah's Instruction to Guests to Eat Before Leaving",
          "display_title": "Abaye's Account",
          "timestamp": "22:57"
        },
        {
          "title": "The Debate Over What Constitutes Seudah: Bread vs. Mezonot",
          "display_title": "Bread vs. Mezonot",
          "timestamp": "25:37"
        },
        {
          "title": "The Dispute Between Tosafot and the Geonim on Minimum Seudah Requirements",
          "display_title": "Tosafot vs. Geonim",
          "timestamp": "26:47"
        },
        {
          "title": "Modern Practice: Making Kiddush Again at Home Despite Shul Kiddush",
          "display_title": "Home Kiddush Practice",
          "timestamp": "28:37"
        },
        {
          "title": "Rambam's Position: Wine Required for All Shabbat Meals",
          "display_title": "Rambam on Wine",
          "timestamp": "31:46"
        },
        {
          "title": "Rabbah's Consistency: Ruling Like Shmuel on Three Specific Issues",
          "display_title": "Rabbah's Three Rulings",
          "timestamp": "33:03"
        },
        {
          "title": "The Three Cases of Rabbah Ruling Like Shmuel: Tzitzit, Chanukah Candles, and Geirah",
          "display_title": "Three Cases",
          "timestamp": "33:03"
        }
      ]
    },
    {
      "title": "Shinuy Makom and the Requirement for New Berachot: Yochanan vs. Chazal on Wine and Location Changes (continued)",
      "display_title": "Shinuy Makom…",
      "timestamp": "36:34",
      "micro_segments": [
        {
          "title": "Rabbi Yochanan's Position: Shinuy Yayin and Shinuy Makom Do Not Require New Beracha",
          "display_title": "Yochanan's Position",
          "timestamp": "36:34"
        },
        {
          "title": "Refutation of Yochanan: A Braisa Establishing That Shinuy Makom Requires New Beracha",
          "display_title": "Refutation of Yochanan",
          "timestamp": "38:25"
        },
        {
          "title": "Rav Chisda's First Teaching: Distinguishing Bayit L'Bayit from Mipina L'Pina",
          "display_title": "Rav Chisda's First Teach…",
          "timestamp": "39:07"
        },
        {
          "title": "Rav Chisda's Second Teaching: Distinction Between Items Requiring Beracha Acharona",
          "display_title": "Rav Chisda's Second Teac…",
          "timestamp": "42:51"
        },
        {
          "title": "The Principle of Lekviat Kama Hadar: Returning to Original Fixed Meal",
          "display_title": "Lekviat Kama Hadar",
          "timestamp": "43:22"
        },
        {
          "title": "Application to Bread and Mezonot: Requiring Return to Original Location for Beracha Achrona",
          "display_title": "Bread/Mezonot Application",
          "timestamp": "44:13"
        },
        {
          "title": "Tosafot's Debate: Which Items Require Returning to Original Location for Beracha",
          "display_title": "Tosafot's Debate",
          "timestamp": "45:05"
        },
        {
          "title": "Rav Sheshet's Strict Position: Always Require New Beracha on Shinuy Makom",
          "display_title": "Rav Sheshet's Position",
          "timestamp": "50:17"
        },
        {
          "title": "The Case of Chavura Members: Different Rules If Someone Is Left Behind",
          "display_title": "Chavura Case",
          "timestamp": "52:08"
        },
        {
          "title": "Distinction Between Rabbi Yehuda and Chachamim on Shinuy Makom Interrupting a Meal",
          "display_title": "Yehuda vs. Chachamim",
          "timestamp": "55:40"
        }
      ]
    }
  ],
  "topical_tags": [
    {
      "term": "Kiddush",
      "timestamps": [
        "01:01",
        "01:14",
        "02:04",
        "02:14",
        "02:57",
        "03:38",
        "04:40",
        "05:53",
        "06:01",
        "08:01",
        "09:02",
        "12:01",
        "13:12",
        "15:08",
        "18:40",
        "28:37",
        "36:34"
      ]
    },
    {
      "term": "Makom Seudah (Place of the Meal)",
      "timestamps": [
        "03:38",
        "04:40",
        "10:03",
        "12:01",
        "12:06",
        "13:12",
        "15:08",
        "16:36",
        "32:34",
        "44:19"
      ]
    },
    {
      "term": "Rav vs. Shmuel",
      "timestamps": [
        "01:14",
        "02:04",
        "02:14",
        "02:57",
        "33:03",
        "35:20"
      ]
    },
    {
      "term": "Shinuy Makom (Change of Location)",
      "timestamps": [
        "01:46",
        "13:41",
        "39:07",
        "42:51",
        "43:22",
        "50:17",
        "52:08",
        "55:40"
      ]
    },
    {
      "term": "Yetziat (Fulfilling Obligation)",
      "timestamps": [
        "01:14",
        "02:04",
        "02:27",
        "04:28",
        "09:02"
      ]
    },
    {
      "term": "Borei Pri Hagafen (Blessing on Wine)",
      "timestamps": [
        "01:35",
        "05:26",
        "11:13",
        "36:34",
        "37:06",
        "38:08"
      ]
    },
    {
      "term": "Shul (Synagogue)",
      "timestamps": [
        "01:07",
        "01:11",
        "02:16",
        "03:08",
        "05:53",
        "16:31",
        "18:46"
      ]
    },
    {
      "term": "Tosafot",
      "timestamps": [
        "01:29",
        "03:17",
        "04:40",
        "09:02",
        "15:08",
        "16:36",
        "17:50",
        "18:02",
        "26:47",
        "35:57",
        "37:34",
        "45:05"
      ]
    },
    {
      "term": "Rashbam",
      "timestamps": [
        "01:29",
        "12:06",
        "37:37",
        "44:46"
      ]
    },
    {
      "term": "Rav Huna",
      "timestamps": [
        "21:45",
        "21:50",
        "22:01"
      ]
    },
    {
      "term": "Rabbah",
      "timestamps": [
        "22:01",
        "22:16",
        "22:51",
        "31:46",
        "33:03"
      ]
    },
    {
      "term": "Abaye",
      "timestamps": [
        "22:57",
        "32:53"
      ]
    },
    {
      "term": "Shmuel",
      "timestamps": [
        "02:04",
        "02:57",
        "03:38",
        "13:41",
        "20:56",
        "33:03"
      ]
    },
    {
      "term": "Rabbi Yochanan",
      "timestamps": [
        "36:34",
        "36:59",
        "37:00"
      ]
    },
    {
      "term": "Rav Anan bar Tachlifa",
      "timestamps": [
        "13:41"
      ]
    },
    {
      "term": "Rav Chisda",
      "timestamps": [
        "39:07",
        "42:51"
      ]
    },
    {
      "term": "Rav Sheshet",
      "timestamps": [
        "50:17"
      ]
    },
    {
      "term": "Mezonot (Light Foods)",
      "timestamps": [
        "04:15",
        "04:21",
        "04:25",
        "04:32",
        "26:47",
        "27:09",
        "44:13"
      ]
    },
    {
      "term": "Seudot Shabbat (Shabbat Meals)",
      "timestamps": [
        "26:51",
        "26:55",
        "26:59",
        "31:46"
      ]
    },
    {
      "term": "Ein Kiddush Ela Bimkom Seuda (Kiddush Only Where There Is a Meal)",
      "timestamps": [
        "02:10",
        "03:41",
        "12:01",
        "24:03"
      ]
    },
    {
      "term": "Hamotzi (Blessing on Bread)",
      "timestamps": [
        "11:37",
        "11:40",
        "28:45",
        "44:23",
        "53:09",
        "54:09"
      ]
    },
    {
      "term": "Bracha Rishona (First Blessing)",
      "timestamps": [
        "50:32",
        "50:43"
      ]
    },
    {
      "term": "Bracha Achrona (Final Blessing)",
      "timestamps": [
        "30:45",
        "44:31",
        "44:42",
        "44:51"
      ]
    },
    {
      "term": "Geonim (Medieval Jewish Scholars)",
      "timestamps": [
        "26:03",
        "26:09"
      ]
    },
    {
      "term": "Rambam",
      "timestamps": [
        "31:46",
        "31:50",
        "32:04"
      ]
    },
    {
      "term": "Chachamim (Sages)",
      "timestamps": [
        "34:00",
        "55:46",
        "56:01"
      ]
    },
    {
      "term": "Rabbi Yehuda",
      "timestamps": [
        "34:03",
        "55:40",
        "55:46"
      ]
    },
    {
      "term": "Keviut Seuda (Fixed Meal)",
      "timestamps": [
        "43:29",
        "56:04"
      ]
    },
    {
      "term": "Chazarat HaShatz (Repetition of the Prayer)",
      "timestamps": [
        "06:17",
        "07:03",
        "07:18"
      ]
    },
    {
      "term": "Shbat Shabbos (Shabbat Meal)",
      "timestamps": [
        "29:32",
        "32:34"
      ]
    },
    {
      "term": "Bayit L'Bayit (House to House)",
      "timestamps": [
        "16:28",
        "39:16",
        "41:14"
      ]
    },
    {
      "term": "Mipina L'Pina (Corner to Corner)",
      "timestamps": [
        "15:57",
        "39:33",
        "41:16"
      ]
    },
    {
      "term": "Lekviat Kama Hadar (Returning to Original Established Meal)",
      "timestamps": [
        "43:22",
        "48:10"
      ]
    },
    {
      "term": "Braita (Tannaitic Teaching)",
      "timestamps": [
        "38:33",
        "40:01",
        "40:11"
      ]
    },
    {
      "term": "Hatov Vehametiv (Blessing on Improved Wine)",
      "timestamps": [
        "37:32",
        "37:45",
        "37:47"
      ]
    },
    {
      "term": "Shomea K'Oneh (Listening as if Answering)",
      "timestamps": [
        "08:16",
        "08:32",
        "08:38"
      ]
    }
  ]
}