{
  "masechta": "Pesachim",
  "daf": 84,
  "amud": "",
  "macro_segments": [
    {
      "title": "Definition of Meat (Basar) in the Korban Pesach: The Principle of Future Edibility",
      "display_title": "Definition of Meat",
      "timestamp": "01:02",
      "micro_segments": [
        {
          "title": "Introduction to the Mishnah: What Constitutes Meat in a Young Animal",
          "display_title": "Meat Definition Intro",
          "timestamp": "01:02"
        },
        {
          "title": "Mishnah Reading: 'Kol Hane'echal Beshor Gadol' - Comparative Standard with Large Animals",
          "display_title": "Comparative Standard",
          "timestamp": "01:18"
        },
        {
          "title": "Cartilage and Bones: Rashei Knafayim and Sachchusim Included as Meat",
          "display_title": "Cartilage Analysis",
          "timestamp": "02:19"
        },
        {
          "title": "Artscroll Note: Cartilage Transformation from Soft Tissue to Hard Bone",
          "display_title": "Cartilage Hardening",
          "timestamp": "03:10"
        }
      ]
    },
    {
      "title": "The Gemara's Challenge: Apparent Contradiction Within the Mishnah",
      "display_title": "Mishnah Contradiction",
      "timestamp": "05:13",
      "micro_segments": [
        {
          "title": "Rabba's Contradiction: How Can Both Parts of the Mishnah Be True?",
          "display_title": "Rabba's Challenge",
          "timestamp": "05:13"
        },
        {
          "title": "Gemara's Resolution: Two Conflicting Tannaim Pasted Together",
          "display_title": "Tannaim Debate",
          "timestamp": "05:53"
        },
        {
          "title": "Rava's Explanation: Boiling (Shalka) as the Edibility Standard",
          "display_title": "Rava's Shalka",
          "timestamp": "08:14"
        }
      ]
    },
    {
      "title": "Rabbi Yochanan vs. Reish Lakish: Current Status vs. Future Status of Sinews",
      "display_title": "Yochanan/Lakish Debate",
      "timestamp": "12:00",
      "micro_segments": [
        {
          "title": "Itmar: A Separate Discussion on Sinews That Will Harden (Gidim Shesofam Lehakshot)",
          "display_title": "Hardening Sinews",
          "timestamp": "12:00"
        },
        {
          "title": "Rabbi Yochanan: Sinews Count as Meat (Nimnim Aleihem) for Pesach",
          "display_title": "Yochanan Position",
          "timestamp": "13:08"
        },
        {
          "title": "Reish Lakish: Sinews Cannot Count (Ein Nimnim) - Future Status Determines Classification",
          "display_title": "Lakish Position",
          "timestamp": "13:18"
        },
        {
          "title": "The Contradiction Challenge: How Does Yochanan Reconcile His Position with the Mishnah?",
          "display_title": "Yochanan's Reconciliation",
          "timestamp": "14:47"
        },
        {
          "title": "Rabbi Yochanan's Response: Liberal Definition of 'Edible' Including Boiled Meat",
          "display_title": "Liberal Edibility",
          "timestamp": "15:31"
        }
      ]
    },
    {
      "title": "The Parallels in Chulin: Skin of the Head and the Question of Food Status",
      "display_title": "Chulin Parallels",
      "timestamp": "17:06",
      "micro_segments": [
        {
          "title": "Rav Yirmeyah's Challenge to Rabbi Abbahu: Does Rabbi Yochanan Really Hold This Position?",
          "display_title": "Abbahu Challenge",
          "timestamp": "17:06"
        },
        {
          "title": "The Chulin Precedent: Skin of a Tender Calf and Tum'ah Status",
          "display_title": "Skin Precedent",
          "timestamp": "17:38"
        },
        {
          "title": "Rabbi Abbahu's Response: Criticism of the Question's Premise",
          "display_title": "Abbahu Response",
          "timestamp": "18:33"
        },
        {
          "title": "Rabbi Yochanan's Reversal: From Present Status to Future Status",
          "display_title": "Yochanan Reversal",
          "timestamp": "20:38"
        }
      ]
    },
    {
      "title": "The Rambam's Understanding: Meat vs. Partnership in the Korban",
      "display_title": "Rambam Analysis",
      "timestamp": "24:32",
      "micro_segments": [
        {
          "title": "Rambam Hilchot Chametz U'Matzah 8:11: Soft Sinews and Participatory Rights",
          "display_title": "Rambam's Position",
          "timestamp": "24:32"
        },
        {
          "title": "Distinction: Edible as Meat vs. Sufficient for Partnership (Nmuin Aleihem)",
          "display_title": "Meat/Partnership",
          "timestamp": "25:02"
        },
        {
          "title": "Practical Instructions: Roasting the Pesach Whole with the Gid HaNasheh Inside",
          "display_title": "Roasting Procedure",
          "timestamp": "25:47"
        },
        {
          "title": "Ra'avad's Objection: Prohibition Against Roasting with Gid and Forbidden Fats",
          "display_title": "Ra'avad Objection",
          "timestamp": "27:38"
        }
      ]
    },
    {
      "title": "Leaving Over Meat (Nosar) and Breaking Bones (Sheviras Etzem): Discrete Prohibitions",
      "display_title": "Nosar/Sheviras",
      "timestamp": "29:33",
      "micro_segments": [
        {
          "title": "Mishnah: Breaking Bones in a Kosher Pesach Incurs Lashes; Leaving Over Meat Does Not",
          "display_title": "Lashes Distinction",
          "timestamp": "29:33"
        },
        {
          "title": "Gemara Analysis: Why Leaving Over Meat Does Not Incur Lashes",
          "display_title": "Nosar Exemption",
          "timestamp": "29:41"
        },
        {
          "title": "Rav Ami's Case: Pesach Brought in Tumah - Where Does the Machlokes Apply?",
          "display_title": "Tumah Pesach",
          "timestamp": "33:02"
        },
        {
          "title": "Abaye and Rav Yosef: Resolving Disputes Over the Scope of the Machlokes",
          "display_title": "Scope Resolution",
          "timestamp": "35:31"
        }
      ]
    },
    {
      "title": "Breaking Bones Before the Proper Time: The Fourteenth vs. the Fifteenth",
      "display_title": "Timing Issues",
      "timestamp": "36:02",
      "micro_segments": [
        {
          "title": "The Case of Breaking Before Nightfall on the Fourteenth",
          "display_title": "14th Breaking",
          "timestamp": "36:02"
        },
        {
          "title": "Marrow Extraction: Why Moach Shebarosh Is Permissible But Not Moach Shebekullis",
          "display_title": "Marrow Cases",
          "timestamp": "36:35"
        },
        {
          "title": "Burning Bones as Alternative: Pak Paka and Hefsed Kodashim Concerns",
          "display_title": "Burning Alternative",
          "timestamp": "38:42"
        },
        {
          "title": "Rabbinical Safeguard: Gezeirah Against Breaking Bones Even Before Nightfall",
          "display_title": "Rabbinical Safeguard",
          "timestamp": "40:45"
        }
      ]
    },
    {
      "title": "Partial Disqualification and Specialized Cases: Half-Limb and Stripped Bones",
      "display_title": "Partial Disqualification",
      "timestamp": "41:58",
      "micro_segments": [
        {
          "title": "Rabbi Yishmael ben Yochanan ben Beroka: Half-Limb Protruding Beyond Yerushalayim Boundary",
          "display_title": "Half-Limb Case",
          "timestamp": "41:58"
        },
        {
          "title": "Breaking of the Fat Tail (Aliyah): Different Standards Applied to Sacrificial Parts",
          "display_title": "Fat Tail Case",
          "timestamp": "45:37"
        },
        {
          "title": "Limb Stripped of Meat: The Requirement of a Kezayit (Olive-Size) for Prohibition",
          "display_title": "Stripped Limb",
          "timestamp": "47:34"
        },
        {
          "title": "Meat Distribution: When Kezayit Exists But Not at the Point of Breaking",
          "display_title": "Meat Distribution",
          "timestamp": "49:37"
        },
        {
          "title": "Internal vs. External Meat: Marrow Inside Can Satisfy the Kezayit Requirement",
          "display_title": "Internal Marrow",
          "timestamp": "49:45"
        }
      ]
    },
    {
      "title": "The Beraita and Final Debate: Rabbi Yochanan vs. Reish Lakish on Meat Location",
      "display_title": "Final Beraita",
      "timestamp": "50:25",
      "micro_segments": [
        {
          "title": "Beraita Formulation: Four Different Standards for When Sheviras Etzem Applies",
          "display_title": "Four Standards",
          "timestamp": "50:25"
        },
        {
          "title": "Rebbi's Position: Kezayit Requirement and Qualification of Meat for Altar",
          "display_title": "Rebbi Standard",
          "timestamp": "50:35"
        },
        {
          "title": "The Continued Debate: Rabbi Yochanan Holds Meat Anywhere; Reish Lakish Holds Meat Only at Breakpoint",
          "display_title": "Location Debate",
          "timestamp": "51:59"
        },
        {
          "title": "Final Challenge and Clarification: Distinguishing Meat on the Outside from Marrow on the Inside",
          "display_title": "Outside/Inside",
          "timestamp": "52:04"
        }
      ]
    }
  ],
  "topical_tags": [
    {
      "term": "Basar (Meat) - Definition and Edibility Standards",
      "timestamps": [
        "01:02",
        "01:18",
        "02:19",
        "05:13",
        "08:14",
        "24:32"
      ]
    },
    {
      "term": "Kol Hane'echal Beshor Gadol - Comparative Standard with Large Animals",
      "timestamps": [
        "01:18",
        "02:00",
        "05:16",
        "05:20"
      ]
    },
    {
      "term": "Gidim Harachim / Gidim Shesofam Lehakshot (Soft Sinews / Sinews That Will Harden)",
      "timestamps": [
        "00:25",
        "11:43",
        "12:00",
        "13:03",
        "15:01",
        "24:45"
      ]
    },
    {
      "term": "Nimnim Aleihem (Count as Meat / Partnership in Pesach)",
      "timestamps": [
        "13:10",
        "13:18",
        "13:40",
        "14:06",
        "24:56"
      ]
    },
    {
      "term": "Rabbi Yochanan vs. Reish Lakish - Present vs. Future Status",
      "timestamps": [
        "13:08",
        "13:18",
        "14:47",
        "15:01",
        "51:59"
      ]
    },
    {
      "term": "Shalka (Boiling) - Alternative Method of Edibility",
      "timestamps": [
        "08:22",
        "09:20",
        "15:40"
      ]
    },
    {
      "term": "Rambam - Halchic Ruling and Practice",
      "timestamps": [
        "23:37",
        "24:32",
        "25:47"
      ]
    },
    {
      "term": "Ra'avad - Objection to Rambam's Position",
      "timestamps": [
        "27:38"
      ]
    },
    {
      "term": "Nosar (Leftover Meat) - Burning Requirement",
      "timestamps": [
        "00:15",
        "02:11",
        "04:22",
        "29:33",
        "29:41"
      ]
    },
    {
      "term": "Sheviras Etzem (Breaking Bones) - Prohibition and Lashes",
      "timestamps": [
        "23:41",
        "29:33",
        "32:04",
        "33:20",
        "36:02",
        "41:14"
      ]
    },
    {
      "term": "Pesach Tahor vs. Pesach Tamei - Kosher vs. Impure Pesach",
      "timestamps": [
        "23:51",
        "33:02"
      ]
    },
    {
      "term": "Kasher / Pasul (Kosher / Disqualified) - Status of the Korban",
      "timestamps": [
        "33:05",
        "33:06",
        "34:37",
        "41:58"
      ]
    },
    {
      "term": "Tumah (Impurity) - Dechuyah vs. Hutra in Communal Context",
      "timestamps": [
        "33:17"
      ]
    },
    {
      "term": "Mibod Yom (Before Nightfall on the 14th) - Timing Issue",
      "timestamps": [
        "36:02",
        "36:34",
        "40:49"
      ]
    },
    {
      "term": "Moach Shebarosh vs. Moach Shebekullis (Brain Marrow vs. Thigh Bone Marrow)",
      "timestamps": [
        "36:35",
        "36:50",
        "37:09"
      ]
    },
    {
      "term": "Pak Paka (Crackling from Heat) - Fear of Indirect Transgression",
      "timestamps": [
        "39:13"
      ]
    },
    {
      "term": "Hefsed Kodashim (Destruction of Sacred Objects) - Concern",
      "timestamps": [
        "39:48"
      ]
    },
    {
      "term": "Gzeirah (Rabbinical Decree) - Protection Against Future Transgression",
      "timestamps": [
        "40:49"
      ]
    },
    {
      "term": "Rabbi Yishmael ben Yochanan ben Beroka - Opinion on Half-Limb",
      "timestamps": [
        "43:34"
      ]
    },
    {
      "term": "Alyah (Fat Tail) - Sacrificial Part Analysis",
      "timestamps": [
        "45:37"
      ]
    },
    {
      "term": "Kezayit (Olive-Size) - Minimum Measure for Prohibition",
      "timestamps": [
        "47:34",
        "47:47",
        "48:07",
        "48:18",
        "49:37",
        "49:45"
      ]
    },
    {
      "term": "Sheiur Achilah (Amount Fit to Eat) - Requirement for Obligation",
      "timestamps": [
        "48:11",
        "50:04",
        "51:13"
      ]
    },
    {
      "term": "Beraita Teaching - Four Standards for Sheviras Etzem",
      "timestamps": [
        "50:25"
      ]
    },
    {
      "term": "Moach Mibifnim (Marrow from Inside) - Satisfying Kezayit Requirement",
      "timestamps": [
        "49:45",
        "52:07"
      ]
    }
  ]
}