{
  "masechta": "Bava Batra",
  "daf": 93,
  "amud": "b",
  "macro_segments": [
    {
      "title": "The Debate of Rav and Shmuel: Does Majority Constitute Proof in Monetary Disputes (Holchin B'Mamon Achar Ha'Rov)?",
      "display_title": "Rav vs. Shmuel",
      "timestamp": "00:00",
      "micro_segments": [
        {
          "title": "Introduction to the Core Debate: A Goring Ox as Mekach Taus",
          "display_title": "Goring Ox Case",
          "timestamp": "00:00"
        },
        {
          "title": "Generalizing the Debate: Holchin B'Mamon Achar Ha'Rov and the Burden of Proof",
          "display_title": "Holchin B'Mamon",
          "timestamp": "00:33"
        },
        {
          "title": "Rav's Position: Majority Constitutes Proof Against Chazaka",
          "display_title": "Rav's Position",
          "timestamp": "01:19"
        },
        {
          "title": "Shmuel's Position: Majority Does Not Overcome Chazaka in Monetary Disputes",
          "display_title": "Shmuel's Position",
          "timestamp": "01:30"
        }
      ]
    },
    {
      "title": "The Slave with Defects: Attempting to Prove the Debate Through Talmudic Precedent",
      "display_title": "Slave Defects",
      "timestamp": "02:00",
      "micro_segments": [
        {
          "title": "The Case of a Slave Found to Be a Burglar or Gambler (Kubyustos)",
          "display_title": "Slave Flaws",
          "timestamp": "02:00"
        },
        {
          "title": "Buyer Beware Principle: Minor Defects vs. Severe Conditions (Death Sentence)",
          "display_title": "Buyer Beware",
          "timestamp": "02:44"
        },
        {
          "title": "Gemara's Challenge: Is the Slave Case Really About Majority or About Something Else?",
          "display_title": "Gemara Analysis",
          "timestamp": "04:04"
        },
        {
          "title": "The Gemara's Rejection: All Slaves Are Like That, Not Just the Majority",
          "display_title": "Rejection",
          "timestamp": "04:47"
        }
      ]
    },
    {
      "title": "The Pregnant Cow Gored and the Question of Miscarriage: Rov vs. Safek in Causation",
      "display_title": "Pregnant Cow Case",
      "timestamp": "06:04",
      "micro_segments": [
        {
          "title": "The Case of an Ox Goring a Pregnant Cow: When Did the Miscarriage Occur?",
          "display_title": "Goring Pregnant",
          "timestamp": "06:04"
        },
        {
          "title": "The Sumchus Position: Mamona Hamutal B'Safek Cholkin (Splitting the Difference)",
          "display_title": "Sumchus Splits",
          "timestamp": "07:54"
        },
        {
          "title": "Can Rov Determine What Happened? The Gemara's Challenge",
          "display_title": "Rov Challenge",
          "timestamp": "09:18"
        },
        {
          "title": "Distinguishing Between Goring and Fear: The Safek Within the Rov",
          "display_title": "Fear vs. Goring",
          "timestamp": "10:00"
        },
        {
          "title": "Tosafot's Framing: Multiple Possibilities Create a Safek Despite Rov",
          "display_title": "Tosafot's Analysis",
          "timestamp": "11:55"
        },
        {
          "title": "Conclusion: The Case Does Not Prove the Debate Because a True Rov Is Lacking",
          "display_title": "No Proof Here",
          "timestamp": "13:12"
        }
      ]
    },
    {
      "title": "The Debated Tannaim: Ox with Propensity to Gore (Chazaka) vs. Camel in Heat",
      "display_title": "Chazaka Tannaim",
      "timestamp": "14:33",
      "micro_segments": [
        {
          "title": "An Ox Known to Gore Found Near a Dead Ox: Circumstantial Evidence",
          "display_title": "Ox Propensity",
          "timestamp": "14:33"
        },
        {
          "title": "Rabbi Acha's Position: Even Without Direct Knowledge, Use Circumstantial Evidence",
          "display_title": "Rabbi Acha",
          "timestamp": "16:10"
        },
        {
          "title": "Hypothetical Connection to Rav and Shmuel's Debate on Rov and Chazaka",
          "display_title": "Connection Test",
          "timestamp": "18:33"
        },
        {
          "title": "Rav's Clarification: Rov Can Be Used Without Chazaka, and Vice Versa",
          "display_title": "Rav's Clarification",
          "timestamp": "19:41"
        },
        {
          "title": "Shmuel's Clarification: Chazaka (Propensity) Is Weightier Than General Rov (Statistics)",
          "display_title": "Shmuel's Clarification",
          "timestamp": "20:26"
        },
        {
          "title": "The Conceptual Difference: Propensity About Specific Individuals vs. General Statistics",
          "display_title": "Rov vs. Chazaka",
          "timestamp": "21:20"
        }
      ]
    },
    {
      "title": "Flaxseed as a Test Case: Does Majority Usage Constitute Mekach Taus?",
      "display_title": "Flaxseed Debate",
      "timestamp": "25:00",
      "micro_segments": [
        {
          "title": "The Mishnah: Even Flaxseed (Which Most Buy for Planting) Does Not Constitute Mekach Taus",
          "display_title": "Mishnah Rule",
          "timestamp": "25:00"
        },
        {
          "title": "The Baraita Positions: Tanna Kamma and Rabbi Yossi on When to Apply Mekach Taus",
          "display_title": "Baraita Views",
          "timestamp": "26:34"
        },
        {
          "title": "The Amru Lo Objection: Many People Buy Flaxseed for Other Purposes",
          "display_title": "Amru Lo",
          "timestamp": "27:31"
        },
        {
          "title": "Gemara's Reframing: Is It the Majority of People or the Majority of Seeds?",
          "display_title": "Two Rovs",
          "timestamp": "28:56"
        },
        {
          "title": "Conclusion: The Mishnah Represents Shmuel's Position; Rabbi Yossi and Amru Lo Represent Rav",
          "display_title": "Positions Aligned",
          "timestamp": "30:46"
        }
      ]
    },
    {
      "title": "Liability for Defective Products: From Seeds to Catering and Professional Negligence",
      "display_title": "Professional Liability",
      "timestamp": "32:01",
      "micro_segments": [
        {
          "title": "Reimbursement for Mekach Taus: Seed Cost Only or Including Expenses?",
          "display_title": "What to Reimburse",
          "timestamp": "32:01"
        },
        {
          "title": "The Tanna Kamma vs. Yesh Omrim: Seed Cost Only vs. Including Farmer's Expenses",
          "display_title": "Expense Debate",
          "timestamp": "33:21"
        },
        {
          "title": "Rav Chisda's Attribution: Yesh Omrim Is the Position of Rabban Shimon ben Gamliel",
          "display_title": "Rabban Shimon",
          "timestamp": "34:19"
        },
        {
          "title": "The Baraita of the Miller, Baker, and Butcher: Professional Negligence and Liability",
          "display_title": "Tradespeople",
          "timestamp": "37:31"
        },
        {
          "title": "The Catering Disaster: Rabban Shimon ben Gamliel's Broader Liability for Embarrassment",
          "display_title": "Catering Damages",
          "timestamp": "41:58"
        },
        {
          "title": "The Tablecloth Custom: A Beautiful Jerusalem Practice for Welcoming Guests",
          "display_title": "Tablecloth Custom",
          "timestamp": "43:48"
        },
        {
          "title": "Conceptual Basis: Professional Liability and Foreseeability of Consequential Damages",
          "display_title": "Foreseeability",
          "timestamp": "45:08"
        }
      ]
    },
    {
      "title": "The Debate on Shomer Liability: Negligence Standard and the Nature of Adam Hamazik",
      "display_title": "Shomer Liability",
      "timestamp": "47:01",
      "micro_segments": [
        {
          "title": "Why Is Liability for Craftspeople Tied to Payment Status?",
          "display_title": "Payment Status",
          "timestamp": "47:01"
        },
        {
          "title": "Tosafot's Position: Adam Hamazik Requires Some Negligence; Complete Ones Is Exempt",
          "display_title": "Tosafot View",
          "timestamp": "47:46"
        },
        {
          "title": "Ramban's Position: Liability Depends on the Relationship to the Object (Uman vs. Mazik)",
          "display_title": "Ramban View",
          "timestamp": "48:20"
        },
        {
          "title": "The Ramban's Alternative Approach: Responsibility of the Damaged Party (Peshias Hanizak)",
          "display_title": "Ramban Alternative",
          "timestamp": "50:23"
        }
      ]
    },
    {
      "title": "Standard Allowances for Defective Goods: Dirt, Worms, and Mixed Legumes in Produce",
      "display_title": "Produce Standards",
      "timestamp": "50:55",
      "micro_segments": [
        {
          "title": "Introduction: The Mishnah's List of Acceptable Defect Rates in Agricultural Products",
          "display_title": "Defect Rates",
          "timestamp": "50:55"
        },
        {
          "title": "Wheat and Chaff: A Quarter Kav of Extraneous Material Per Se'ah (About 4 Percent)",
          "display_title": "Wheat Standard",
          "timestamp": "51:57"
        },
        {
          "title": "Figs: Up to 10 Percent Wormy (Mesulaos)",
          "display_title": "Figs Standard",
          "timestamp": "52:24"
        },
        {
          "title": "Wine Cellar: Up to 10 Percent Spoiled Barrels",
          "display_title": "Wine Standard",
          "timestamp": "52:47"
        },
        {
          "title": "Jugs in Sharon Valley: Up to 10 Percent Imperfect (Pitzetzos)",
          "display_title": "Jugs Standard",
          "timestamp": "54:06"
        },
        {
          "title": "Rav Katina's Teaching: Legumes and Wild Plants vs. Pure Dirt—Different Standards",
          "display_title": "Legumes vs. Dirt",
          "timestamp": "54:27"
        },
        {
          "title": "The Distinction: Legumes and Mixed Vegetation Are Anticipated; Dirt Is Not",
          "display_title": "Mixed Vegetation",
          "timestamp": "55:16"
        }
      ]
    }
  ],
  "topical_tags": [
    {
      "term": "Rav vs. Shmuel",
      "timestamps": [
        "00:09",
        "01:19",
        "01:30",
        "19:41",
        "20:26"
      ]
    },
    {
      "term": "Holchin B'Mamon Achar Ha'Rov",
      "timestamps": [
        "00:46",
        "01:48",
        "18:25",
        "28:30",
        "31:40"
      ]
    },
    {
      "term": "Mekach Taus",
      "timestamps": [
        "00:19",
        "01:41",
        "04:04",
        "25:00",
        "31:33"
      ]
    },
    {
      "term": "Chazaka",
      "timestamps": [
        "01:10",
        "05:10",
        "18:45",
        "20:26",
        "21:20"
      ]
    },
    {
      "term": "Rov vs. Chazaka",
      "timestamps": [
        "18:40",
        "20:14",
        "21:20",
        "22:47"
      ]
    },
    {
      "term": "Goring Ox",
      "timestamps": [
        "00:09",
        "06:04",
        "06:43",
        "14:33"
      ]
    },
    {
      "term": "Safek (Doubt)",
      "timestamps": [
        "08:06",
        "10:18",
        "12:50",
        "13:35"
      ]
    },
    {
      "term": "Sumchus Position",
      "timestamps": [
        "08:06",
        "08:38",
        "09:02"
      ]
    },
    {
      "term": "Propensity (Muad)",
      "timestamps": [
        "15:18",
        "18:57",
        "19:15",
        "20:42",
        "21:01"
      ]
    },
    {
      "term": "Tanna Kamma",
      "timestamps": [
        "18:16",
        "27:01",
        "31:01",
        "34:56",
        "35:21"
      ]
    },
    {
      "term": "Rabbi Yossi",
      "timestamps": [
        "27:08",
        "27:25",
        "28:32",
        "31:08"
      ]
    },
    {
      "term": "Flaxseed (Zera Pishtan)",
      "timestamps": [
        "25:15",
        "25:48",
        "26:52",
        "27:00",
        "27:57",
        "28:32"
      ]
    },
    {
      "term": "Rabban Shimon ben Gamliel",
      "timestamps": [
        "26:39",
        "34:19",
        "34:21",
        "37:09",
        "41:58",
        "42:22"
      ]
    },
    {
      "term": "Professional Liability (Uman)",
      "timestamps": [
        "39:55",
        "40:23",
        "41:49",
        "49:25"
      ]
    },
    {
      "term": "Grama (Indirect Causation)",
      "timestamps": [
        "11:04",
        "32:38",
        "42:36",
        "42:39"
      ]
    },
    {
      "term": "Shomer vs. Adam Hamazik",
      "timestamps": [
        "40:20",
        "47:46",
        "48:23"
      ]
    },
    {
      "term": "Tosafot",
      "timestamps": [
        "02:24",
        "11:55",
        "13:00",
        "47:46"
      ]
    },
    {
      "term": "Ramban",
      "timestamps": [
        "47:01",
        "48:20",
        "50:23"
      ]
    },
    {
      "term": "Defect Allowances in Produce",
      "timestamps": [
        "51:57",
        "52:24",
        "52:47",
        "54:06"
      ]
    },
    {
      "term": "Extraneous Material (Tipul)",
      "timestamps": [
        "51:51",
        "52:03",
        "55:20"
      ]
    }
  ]
}